bijansgithubactionstest/__init__.py
bijansgithubactionstest-0.0.28.dist-info/METADATA
bijansgithubactionstest-0.0.28.dist-info/WHEEL
bijansgithubactionstest-0.0.28.dist-info/top_level.txt
bijansgithubactionstest-0.0.28.dist-info/RECORD
