Metadata-Version: 2.1
Name: bijansgithubactionstest
Version: 0.0.28
Summary: This is a test package.
Home-page: https://gemmaanalytics.com/
Author: Bijan Soltani
Author-email: bijan.soltani+ewah@gemmaanalytics.com
License: UNKNOWN
Platform: UNKNOWN
Classifier: Programming Language :: Python :: 3
Classifier: License :: OSI Approved :: MIT License
Requires-Python: >=3.6
Requires-Dist: yahoofinancials
